[
  {"tid": "training-examples.0", "last_saved": "12/08/2020 19:06:49", "annotator": "jdchoi", "tokens": ["The", "boy", "wants", "to", "be", "believed", "by", "the", "girl", "."], "concepts": {"c2": {"name": "want", "token_ids": [2], "attribute": false}, "c3": {"name": "boy", "token_ids": [1], "attribute": false}, "c4": {"name": "believe", "token_ids": [5], "attribute": false}, "c5": {"name": "girl", "token_ids": [8], "attribute": false}}, "relations": {"r2": {"parent_id": "c2", "child_id": "c3", "label": "ARG0", "referent": false}, "r3": {"parent_id": "c2", "child_id": "c4", "label": "ARG1", "referent": false}, "r4": {"parent_id": "c4", "child_id": "c5", "label": "ARG0", "referent": false}, "r5": {"parent_id": "c4", "child_id": "c3", "label": "ARG1", "referent": true}}, "covered_token_ids": [8, 1, 2, 5], "_concept_id": 6, "_relation_id": 6},
  {"tid": "training-examples.1", "last_saved": "", "annotator": "jdchoi", "tokens": ["the", "machine", "was", "adjusted", "by", "the", "girl", "."], "concepts": {}, "relations": {}, "covered_token_ids": [], "_concept_id": 0, "_relation_id": 0},
  {"tid": "training-examples.2", "last_saved": "", "annotator": "jdchoi", "tokens": ["The", "killing", "took", "place", "yesterday", "."], "concepts": {}, "relations": {}, "covered_token_ids": [], "_concept_id": 0, "_relation_id": 0},
  {"tid": "training-examples.3", "last_saved": "", "annotator": "jdchoi", "tokens": ["the", "boy", "and", "the", "girl"], "concepts": {}, "relations": {}, "covered_token_ids": [], "_concept_id": 0, "_relation_id": 0},
  {"tid": "training-examples.4", "last_saved": "", "annotator": "jdchoi", "tokens": ["his", "boat"], "concepts": {}, "relations": {}, "covered_token_ids": [], "_concept_id": 0, "_relation_id": 0},
  {"tid": "training-examples.5", "last_saved": "", "annotator": "jdchoi", "tokens": ["The", "boy", "must", "not", "go", "."], "concepts": {}, "relations": {}, "covered_token_ids": [], "_concept_id": 0, "_relation_id": 0},
  {"tid": "training-examples.6", "last_saved": "", "annotator": "jdchoi", "tokens": ["The", "boy", "does", "not", "have", "permission", "to", "go", "."], "concepts": {}, "relations": {}, "covered_token_ids": [], "_concept_id": 0, "_relation_id": 0},
  {"tid": "training-examples.7", "last_saved": "", "annotator": "jdchoi", "tokens": ["The", "marble", "is", "white", "."], "concepts": {}, "relations": {}, "covered_token_ids": [], "_concept_id": 0, "_relation_id": 0},
  {"tid": "training-examples.8", "last_saved": "", "annotator": "jdchoi", "tokens": ["the", "white", "marble"], "concepts": {}, "relations": {}, "covered_token_ids": [], "_concept_id": 0, "_relation_id": 0},
  {"tid": "training-examples.9", "last_saved": "", "annotator": "jdchoi", "tokens": ["the", "marble", "that", "is", "white"], "concepts": {}, "relations": {}, "covered_token_ids": [], "_concept_id": 0, "_relation_id": 0},
  {"tid": "training-examples.10", "last_saved": "", "annotator": "jdchoi", "tokens": ["The", "boy", "sees", "the", "witness", "of", "the", "marble", "."], "concepts": {}, "relations": {}, "covered_token_ids": [], "_concept_id": 0, "_relation_id": 0},
  {"tid": "training-examples.11", "last_saved": "", "annotator": "jdchoi", "tokens": ["The", "boy", "sees", "the", "marble", "that", "is", "white", "."], "concepts": {}, "relations": {}, "covered_token_ids": [], "_concept_id": 0, "_relation_id": 0},
  {"tid": "training-examples.12", "last_saved": "", "annotator": "jdchoi", "tokens": ["The", "boy", "saw", "the", "girl", "who", "wanted", "him", "."], "concepts": {}, "relations": {}, "covered_token_ids": [], "_concept_id": 0, "_relation_id": 0},
  {"tid": "training-examples.13", "last_saved": "", "annotator": "jdchoi", "tokens": ["The", "boy", "is", "wanted", "by", "the", "girl", "he", "saw", "."], "concepts": {}, "relations": {}, "covered_token_ids": [], "_concept_id": 0, "_relation_id": 0},
  {"tid": "training-examples.14", "last_saved": "", "annotator": "jdchoi", "tokens": ["The", "regulatory", "documents", "were", "changed", "."], "concepts": {}, "relations": {}, "covered_token_ids": [], "_concept_id": 0, "_relation_id": 0},
  {"tid": "training-examples.15", "last_saved": "", "annotator": "jdchoi", "tokens": ["The", "boy", "wants", "to", "believe", "."], "concepts": {}, "relations": {}, "covered_token_ids": [], "_concept_id": 0, "_relation_id": 0},
  {"tid": "training-examples.16", "last_saved": "", "annotator": "jdchoi", "tokens": ["The", "boy", "believes", "."], "concepts": {}, "relations": {}, "covered_token_ids": [], "_concept_id": 0, "_relation_id": 0},
  {"tid": "training-examples.17", "last_saved": "", "annotator": "jdchoi", "tokens": ["He", "described", "the", "mission", "as", "a", "failure", "."], "concepts": {}, "relations": {}, "covered_token_ids": [], "_concept_id": 0, "_relation_id": 0},
  {"tid": "training-examples.18", "last_saved": "", "annotator": "jdchoi", "tokens": ["a", "band", "of", "marauders"], "concepts": {}, "relations": {}, "covered_token_ids": [], "_concept_id": 0, "_relation_id": 0},
  {"tid": "training-examples.19", "last_saved": "", "annotator": "jdchoi", "tokens": ["It", "is", "possible", "that", "the", "boy", "goes", "."], "concepts": {}, "relations": {}, "covered_token_ids": [], "_concept_id": 0, "_relation_id": 0},
  {"tid": "training-examples.20", "last_saved": "", "annotator": "jdchoi", "tokens": ["The", "boy", "must", "go", "."], "concepts": {}, "relations": {}, "covered_token_ids": [], "_concept_id": 0, "_relation_id": 0},
  {"tid": "training-examples.21", "last_saved": "", "annotator": "jdchoi", "tokens": ["The", "boy", "is", "permitted", "to", "go", "."], "concepts": {}, "relations": {}, "covered_token_ids": [], "_concept_id": 0, "_relation_id": 0},
  {"tid": "training-examples.22", "last_saved": "", "annotator": "jdchoi", "tokens": ["It", "might", "rain", "."], "concepts": {}, "relations": {}, "covered_token_ids": [], "_concept_id": 0, "_relation_id": 0},
  {"tid": "training-examples.23", "last_saved": "", "annotator": "jdchoi", "tokens": ["The", "boy", "should", "go", "."], "concepts": {}, "relations": {}, "covered_token_ids": [], "_concept_id": 0, "_relation_id": 0},
  {"tid": "training-examples.24", "last_saved": "", "annotator": "jdchoi", "tokens": ["The", "boy", "is", "likely", "to", "go", "."], "concepts": {}, "relations": {}, "covered_token_ids": [], "_concept_id": 0, "_relation_id": 0},
  {"tid": "training-examples.25", "last_saved": "", "annotator": "jdchoi", "tokens": ["The", "boy", "prefers", "to", "go", "."], "concepts": {}, "relations": {}, "covered_token_ids": [], "_concept_id": 0, "_relation_id": 0},
  {"tid": "training-examples.26", "last_saved": "", "annotator": "jdchoi", "tokens": ["I", "am", "used", "to", "working", "."], "concepts": {}, "relations": {}, "covered_token_ids": [], "_concept_id": 0, "_relation_id": 0},
  {"tid": "training-examples.27", "last_saved": "", "annotator": "jdchoi", "tokens": ["The", "boy", "does", "n't", "go", "."], "concepts": {}, "relations": {}, "covered_token_ids": [], "_concept_id": 0, "_relation_id": 0},
  {"tid": "training-examples.28", "last_saved": "", "annotator": "jdchoi", "tokens": ["The", "boy", "ca", "n't", "go", "."], "concepts": {}, "relations": {}, "covered_token_ids": [], "_concept_id": 0, "_relation_id": 0},
  {"tid": "training-examples.29", "last_saved": "", "annotator": "jdchoi", "tokens": ["It", "is", "possible", "for", "the", "boy", "to", "not", "go", "."], "concepts": {}, "relations": {}, "covered_token_ids": [], "_concept_id": 0, "_relation_id": 0},
  {"tid": "training-examples.30", "last_saved": "", "annotator": "jdchoi", "tokens": ["It", "is", "not", "necessary", "for", "the", "boy", "to", "go", "."], "concepts": {}, "relations": {}, "covered_token_ids": [], "_concept_id": 0, "_relation_id": 0},
  {"tid": "training-examples.31", "last_saved": "", "annotator": "jdchoi", "tokens": ["The", "boy", "must", "not", "go", "."], "concepts": {}, "relations": {}, "covered_token_ids": [], "_concept_id": 0, "_relation_id": 0},
  {"tid": "training-examples.32", "last_saved": "", "annotator": "jdchoi", "tokens": ["The", "boy", "thinks", "his", "team", "wo", "n't", "win", "."], "concepts": {}, "relations": {}, "covered_token_ids": [], "_concept_id": 0, "_relation_id": 0},
  {"tid": "training-examples.33", "last_saved": "", "annotator": "jdchoi", "tokens": ["The", "boy", "does", "n't", "think", "his", "team", "will", "win", "."], "concepts": {}, "relations": {}, "covered_token_ids": [], "_concept_id": 0, "_relation_id": 0},
  {"tid": "training-examples.34", "last_saved": "", "annotator": "jdchoi", "tokens": ["I", "have", "no", "money", "."], "concepts": {}, "relations": {}, "covered_token_ids": [], "_concept_id": 0, "_relation_id": 0},
  {"tid": "training-examples.35", "last_saved": "", "annotator": "jdchoi", "tokens": ["The", "dress", "is", "inappropriate", "."], "concepts": {}, "relations": {}, "covered_token_ids": [], "_concept_id": 0, "_relation_id": 0},
  {"tid": "training-examples.36", "last_saved": "", "annotator": "jdchoi", "tokens": ["The", "inappropriate", "dress", "."], "concepts": {}, "relations": {}, "covered_token_ids": [], "_concept_id": 0, "_relation_id": 0},
  {"tid": "training-examples.37", "last_saved": "", "annotator": "jdchoi", "tokens": ["What", "did", "the", "girl", "find", "?"], "concepts": {}, "relations": {}, "covered_token_ids": [], "_concept_id": 0, "_relation_id": 0},
  {"tid": "training-examples.38", "last_saved": "", "annotator": "jdchoi", "tokens": ["Where", "did", "the", "girl", "find", "the", "boy", "?"], "concepts": {}, "relations": {}, "covered_token_ids": [], "_concept_id": 0, "_relation_id": 0},
  {"tid": "training-examples.39", "last_saved": "", "annotator": "jdchoi", "tokens": ["How", "did", "the", "girl", "find", "the", "boy", "?"], "concepts": {}, "relations": {}, "covered_token_ids": [], "_concept_id": 0, "_relation_id": 0},
  {"tid": "training-examples.40", "last_saved": "", "annotator": "jdchoi", "tokens": ["Whose", "toy", "did", "the", "girl", "find", "?"], "concepts": {}, "relations": {}, "covered_token_ids": [], "_concept_id": 0, "_relation_id": 0},
  {"tid": "training-examples.41", "last_saved": "", "annotator": "jdchoi", "tokens": ["How", "fast", "did", "the", "girl", "run", "?"], "concepts": {}, "relations": {}, "covered_token_ids": [], "_concept_id": 0, "_relation_id": 0},
  {"tid": "training-examples.42", "last_saved": "", "annotator": "jdchoi", "tokens": ["What", "purple", "thing", "did", "the", "girl", "see", "?"], "concepts": {}, "relations": {}, "covered_token_ids": [], "_concept_id": 0, "_relation_id": 0},
  {"tid": "training-examples.43", "last_saved": "", "annotator": "jdchoi", "tokens": ["Which", "investigation", "did", "she", "lead", "?"], "concepts": {}, "relations": {}, "covered_token_ids": [], "_concept_id": 0, "_relation_id": 0},
  {"tid": "training-examples.44", "last_saved": "", "annotator": "jdchoi", "tokens": ["Did", "the", "girl", "find", "the", "boy", "?"], "concepts": {}, "relations": {}, "covered_token_ids": [], "_concept_id": 0, "_relation_id": 0},
  {"tid": "training-examples.45", "last_saved": "", "annotator": "jdchoi", "tokens": ["Was", "the", "boy", "found", "?"], "concepts": {}, "relations": {}, "covered_token_ids": [], "_concept_id": 0, "_relation_id": 0},
  {"tid": "training-examples.46", "last_saved": "", "annotator": "jdchoi", "tokens": ["I", "know", "who", "you", "saw", "."], "concepts": {}, "relations": {}, "covered_token_ids": [], "_concept_id": 0, "_relation_id": 0},
  {"tid": "training-examples.47", "last_saved": "", "annotator": "jdchoi", "tokens": ["The", "boy", "does", "n't", "know", "if", "the", "girl", "came", "."], "concepts": {}, "relations": {}, "covered_token_ids": [], "_concept_id": 0, "_relation_id": 0},
  {"tid": "training-examples.48", "last_saved": "", "annotator": "jdchoi", "tokens": ["The", "boy", "does", "n't", "know", "that", "the", "girl", "came", "."], "concepts": {}, "relations": {}, "covered_token_ids": [], "_concept_id": 0, "_relation_id": 0},
  {"tid": "training-examples.49", "last_saved": "", "annotator": "jdchoi", "tokens": ["Do", "you", "want", "tea", "or", "coffee", "?"], "concepts": {}, "relations": {}, "covered_token_ids": [], "_concept_id": 0, "_relation_id": 0},
  {"tid": "training-examples.50", "last_saved": "", "annotator": "jdchoi", "tokens": ["Should", "I", "stay", "or", "should", "I", "go", "?"], "concepts": {}, "relations": {}, "covered_token_ids": [], "_concept_id": 0, "_relation_id": 0},
  {"tid": "training-examples.51", "last_saved": "", "annotator": "jdchoi", "tokens": ["Go", "!"], "concepts": {}, "relations": {}, "covered_token_ids": [], "_concept_id": 0, "_relation_id": 0},
  {"tid": "training-examples.52", "last_saved": "", "annotator": "jdchoi", "tokens": ["Let", "'s", "go", "!"], "concepts": {}, "relations": {}, "covered_token_ids": [], "_concept_id": 0, "_relation_id": 0},
  {"tid": "training-examples.53", "last_saved": "", "annotator": "jdchoi", "tokens": ["Yes", "!"], "concepts": {}, "relations": {}, "covered_token_ids": [], "_concept_id": 0, "_relation_id": 0},
  {"tid": "training-examples.54", "last_saved": "", "annotator": "jdchoi", "tokens": ["The", "boy", "will", "go", "."], "concepts": {}, "relations": {}, "covered_token_ids": [], "_concept_id": 0, "_relation_id": 0},
  {"tid": "training-examples.55", "last_saved": "", "annotator": "jdchoi", "tokens": ["those", "boys"], "concepts": {}, "relations": {}, "covered_token_ids": [], "_concept_id": 0, "_relation_id": 0},
  {"tid": "training-examples.56", "last_saved": "", "annotator": "jdchoi", "tokens": ["this", "boy"], "concepts": {}, "relations": {}, "covered_token_ids": [], "_concept_id": 0, "_relation_id": 0},
  {"tid": "training-examples.57", "last_saved": "", "annotator": "jdchoi", "tokens": ["That", "is", "a", "shame", "."], "concepts": {}, "relations": {}, "covered_token_ids": [], "_concept_id": 0, "_relation_id": 0},
  {"tid": "training-examples.58", "last_saved": "", "annotator": "jdchoi", "tokens": ["money", "-", "market", "account"], "concepts": {}, "relations": {}, "covered_token_ids": [], "_concept_id": 0, "_relation_id": 0},
  {"tid": "training-examples.59", "last_saved": "", "annotator": "jdchoi", "tokens": ["vice", "president"], "concepts": {}, "relations": {}, "covered_token_ids": [], "_concept_id": 0, "_relation_id": 0},
  {"tid": "training-examples.60", "last_saved": "", "annotator": "jdchoi", "tokens": ["brother", "-", "in", "-", "law"], "concepts": {}, "relations": {}, "covered_token_ids": [], "_concept_id": 0, "_relation_id": 0},
  {"tid": "training-examples.61", "last_saved": "", "annotator": "jdchoi", "tokens": ["He", "was", "charged", "with", "public", "intoxication", "and", "resisting", "arrest", "."], "concepts": {}, "relations": {}, "covered_token_ids": [], "_concept_id": 0, "_relation_id": 0},
  {"tid": "training-examples.62", "last_saved": "", "annotator": "jdchoi", "tokens": ["the", "hopeful", "girl"], "concepts": {}, "relations": {}, "covered_token_ids": [], "_concept_id": 0, "_relation_id": 0},
  {"tid": "training-examples.63", "last_saved": "", "annotator": "jdchoi", "tokens": ["The", "marble", "is", "small", "."], "concepts": {}, "relations": {}, "covered_token_ids": [], "_concept_id": 0, "_relation_id": 0},
  {"tid": "training-examples.64", "last_saved": "", "annotator": "jdchoi", "tokens": ["The", "man", "is", "a", "lawyer", "."], "concepts": {}, "relations": {}, "covered_token_ids": [], "_concept_id": 0, "_relation_id": 0},
  {"tid": "training-examples.65", "last_saved": "", "annotator": "jdchoi", "tokens": ["The", "man", "who", "is", "a", "lawyer", "."], "concepts": {}, "relations": {}, "covered_token_ids": [], "_concept_id": 0, "_relation_id": 0},
  {"tid": "training-examples.66", "last_saved": "", "annotator": "jdchoi", "tokens": ["There", "is", "a", "boy", "."], "concepts": {}, "relations": {}, "covered_token_ids": [], "_concept_id": 0, "_relation_id": 0},
  {"tid": "training-examples.67", "last_saved": "", "annotator": "jdchoi", "tokens": ["There", "are", "four", "boys", "making", "pies", "."], "concepts": {}, "relations": {}, "covered_token_ids": [], "_concept_id": 0, "_relation_id": 0},
  {"tid": "training-examples.68", "last_saved": "", "annotator": "jdchoi", "tokens": ["The", "boy", "'s", "destruction", "of", "the", "room", "."], "concepts": {}, "relations": {}, "covered_token_ids": [], "_concept_id": 0, "_relation_id": 0},
  {"tid": "training-examples.69", "last_saved": "", "annotator": "jdchoi", "tokens": ["the", "explosion"], "concepts": {}, "relations": {}, "covered_token_ids": [], "_concept_id": 0, "_relation_id": 0},
  {"tid": "training-examples.70", "last_saved": "", "annotator": "jdchoi", "tokens": ["the", "proposal"], "concepts": {}, "relations": {}, "covered_token_ids": [], "_concept_id": 0, "_relation_id": 0},
  {"tid": "training-examples.71", "last_saved": "", "annotator": "jdchoi", "tokens": ["the", "boy", "'s", "opinion"], "concepts": {}, "relations": {}, "covered_token_ids": [], "_concept_id": 0, "_relation_id": 0},
  {"tid": "training-examples.72", "last_saved": "", "annotator": "jdchoi", "tokens": ["investor"], "concepts": {}, "relations": {}, "covered_token_ids": [], "_concept_id": 0, "_relation_id": 0},
  {"tid": "training-examples.73", "last_saved": "", "annotator": "jdchoi", "tokens": ["bond", "investor"], "concepts": {}, "relations": {}, "covered_token_ids": [], "_concept_id": 0, "_relation_id": 0},
  {"tid": "training-examples.74", "last_saved": "", "annotator": "jdchoi", "tokens": ["nerdy", "investor"], "concepts": {}, "relations": {}, "covered_token_ids": [], "_concept_id": 0, "_relation_id": 0},
  {"tid": "training-examples.75", "last_saved": "", "annotator": "jdchoi", "tokens": ["treasurer"], "concepts": {}, "relations": {}, "covered_token_ids": [], "_concept_id": 0, "_relation_id": 0},
  {"tid": "training-examples.76", "last_saved": "", "annotator": "jdchoi", "tokens": ["president"], "concepts": {}, "relations": {}, "covered_token_ids": [], "_concept_id": 0, "_relation_id": 0},
  {"tid": "training-examples.77", "last_saved": "", "annotator": "jdchoi", "tokens": ["The", "boy", "works", "hard", "."], "concepts": {}, "relations": {}, "covered_token_ids": [], "_concept_id": 0, "_relation_id": 0},
  {"tid": "training-examples.78", "last_saved": "", "annotator": "jdchoi", "tokens": ["the", "attractive", "man"], "concepts": {}, "relations": {}, "covered_token_ids": [], "_concept_id": 0, "_relation_id": 0},
  {"tid": "training-examples.79", "last_saved": "", "annotator": "jdchoi", "tokens": ["The", "man", "is", "attractive", "."], "concepts": {}, "relations": {}, "covered_token_ids": [], "_concept_id": 0, "_relation_id": 0},
  {"tid": "training-examples.80", "last_saved": "", "annotator": "jdchoi", "tokens": ["The", "man", "attracts", "women", "."], "concepts": {}, "relations": {}, "covered_token_ids": [], "_concept_id": 0, "_relation_id": 0},
  {"tid": "training-examples.81", "last_saved": "", "annotator": "jdchoi", "tokens": ["The", "solder", "realized", "there", "was", "a", "battle", "."], "concepts": {}, "relations": {}, "covered_token_ids": [], "_concept_id": 0, "_relation_id": 0},
  {"tid": "training-examples.82", "last_saved": "", "annotator": "jdchoi", "tokens": ["The", "boy", "is", "responsible", "for", "doing", "the", "work", "."], "concepts": {}, "relations": {}, "covered_token_ids": [], "_concept_id": 0, "_relation_id": 0},
  {"tid": "training-examples.83", "last_saved": "", "annotator": "jdchoi", "tokens": ["The", "girl", "is", "sad", "."], "concepts": {}, "relations": {}, "covered_token_ids": [], "_concept_id": 0, "_relation_id": 0},
  {"tid": "training-examples.84", "last_saved": "", "annotator": "jdchoi", "tokens": ["The", "disaster", "saddened", "the", "girl", "."], "concepts": {}, "relations": {}, "covered_token_ids": [], "_concept_id": 0, "_relation_id": 0},
  {"tid": "training-examples.85", "last_saved": "", "annotator": "jdchoi", "tokens": ["The", "boy", "is", "acquainted", "with", "magic", "."], "concepts": {}, "relations": {}, "covered_token_ids": [], "_concept_id": 0, "_relation_id": 0},
  {"tid": "training-examples.86", "last_saved": "", "annotator": "jdchoi", "tokens": ["Boys", "want", "to", "please", "."], "concepts": {}, "relations": {}, "covered_token_ids": [], "_concept_id": 0, "_relation_id": 0},
  {"tid": "training-examples.87", "last_saved": "", "annotator": "jdchoi", "tokens": ["It", "is", "easy", "to", "please", "girls", "."], "concepts": {}, "relations": {}, "covered_token_ids": [], "_concept_id": 0, "_relation_id": 0},
  {"tid": "training-examples.88", "last_saved": "", "annotator": "jdchoi", "tokens": ["an", "edible", "sandwich"], "concepts": {}, "relations": {}, "covered_token_ids": [], "_concept_id": 0, "_relation_id": 0},
  {"tid": "training-examples.89", "last_saved": "", "annotator": "jdchoi", "tokens": ["an", "inedible", "sandwich"], "concepts": {}, "relations": {}, "covered_token_ids": [], "_concept_id": 0, "_relation_id": 0},
  {"tid": "training-examples.90", "last_saved": "", "annotator": "jdchoi", "tokens": ["a", "taxable", "fund"], "concepts": {}, "relations": {}, "covered_token_ids": [], "_concept_id": 0, "_relation_id": 0},
  {"tid": "training-examples.91", "last_saved": "", "annotator": "jdchoi", "tokens": ["I", "observed", "the", "army", "moving", "quickly", "."], "concepts": {}, "relations": {}, "covered_token_ids": [], "_concept_id": 0, "_relation_id": 0},
  {"tid": "training-examples.92", "last_saved": "", "annotator": "jdchoi", "tokens": ["I", "hardly", "know", "her", "."], "concepts": {}, "relations": {}, "covered_token_ids": [], "_concept_id": 0, "_relation_id": 0},
  {"tid": "training-examples.93", "last_saved": "", "annotator": "jdchoi", "tokens": ["He", "drove", "west", ",", "from", "Houston", "to", "Austin", "."], "concepts": {}, "relations": {}, "covered_token_ids": [], "_concept_id": 0, "_relation_id": 0},
  {"tid": "training-examples.94", "last_saved": "", "annotator": "jdchoi", "tokens": ["I", "drove", "to", "Indianapolis", "on", "I-65", "."], "concepts": {}, "relations": {}, "covered_token_ids": [], "_concept_id": 0, "_relation_id": 0},
  {"tid": "training-examples.95", "last_saved": "", "annotator": "jdchoi", "tokens": ["I", "drove", "through", "the", "tunnel", "."], "concepts": {}, "relations": {}, "covered_token_ids": [], "_concept_id": 0, "_relation_id": 0},
  {"tid": "training-examples.96", "last_saved": "", "annotator": "jdchoi", "tokens": ["The", "soldier", "hummed", "a", "tune", "for", "the", "girl", "as", "he", "walked", "with", "her", "to", "town", "."], "concepts": {}, "relations": {}, "covered_token_ids": [], "_concept_id": 0, "_relation_id": 0},
  {"tid": "training-examples.97", "last_saved": "", "annotator": "jdchoi", "tokens": ["There", "is", "no", "information", "about", "the", "case", "."], "concepts": {}, "relations": {}, "covered_token_ids": [], "_concept_id": 0, "_relation_id": 0},
  {"tid": "training-examples.98", "last_saved": "", "annotator": "jdchoi", "tokens": ["USC", "Associate", "Professor", "for", "Mathematics", "Jay", "Bartroff"], "concepts": {}, "relations": {}, "covered_token_ids": [], "_concept_id": 0, "_relation_id": 0},
  {"tid": "training-examples.99", "last_saved": "", "annotator": "jdchoi", "tokens": ["He", "worked", "for", "two", "hours", "."], "concepts": {}, "relations": {}, "covered_token_ids": [], "_concept_id": 0, "_relation_id": 0},
  {"tid": "training-examples.100", "last_saved": "", "annotator": "jdchoi", "tokens": ["I", "ate", "pasta", "with", "a", "fork", "."], "concepts": {}, "relations": {}, "covered_token_ids": [], "_concept_id": 0, "_relation_id": 0},
  {"tid": "training-examples.101", "last_saved": "", "annotator": "jdchoi", "tokens": ["Iraq", "launched", "a", "missile", "attack", "."], "concepts": {}, "relations": {}, "covered_token_ids": [], "_concept_id": 0, "_relation_id": 0},
  {"tid": "training-examples.102", "last_saved": "", "annotator": "jdchoi", "tokens": ["She", "talked", "to", "him", "in", "French", "."], "concepts": {}, "relations": {}, "covered_token_ids": [], "_concept_id": 0, "_relation_id": 0},
  {"tid": "training-examples.103", "last_saved": "", "annotator": "jdchoi", "tokens": ["John", "announced", "the", "birth", "of", "his", "son", "on", "Twitter", "."], "concepts": {}, "relations": {}, "covered_token_ids": [], "_concept_id": 0, "_relation_id": 0},
  {"tid": "training-examples.104", "last_saved": "", "annotator": "jdchoi", "tokens": ["The", "boy", "sang", "very", "beautifully", "."], "concepts": {}, "relations": {}, "covered_token_ids": [], "_concept_id": 0, "_relation_id": 0},
  {"tid": "training-examples.105", "last_saved": "", "annotator": "jdchoi", "tokens": ["He", "decorated", "his", "room", "in", "a", "creative", "way", "."], "concepts": {}, "relations": {}, "covered_token_ids": [], "_concept_id": 0, "_relation_id": 0},
  {"tid": "training-examples.106", "last_saved": "", "annotator": "jdchoi", "tokens": ["The", "mayor", "proposed", "to", "lower", "crime", "by", "hiring", "more", "police", "officers", "."], "concepts": {}, "relations": {}, "covered_token_ids": [], "_concept_id": 0, "_relation_id": 0},
  {"tid": "training-examples.107", "last_saved": "", "annotator": "jdchoi", "tokens": ["Nicole", "went", "to", "England", "by", "train", "."], "concepts": {}, "relations": {}, "covered_token_ids": [], "_concept_id": 0, "_relation_id": 0},
  {"tid": "training-examples.108", "last_saved": "", "annotator": "jdchoi", "tokens": ["He", "went", "to", "the", "store", "to", "buy", "wood", "for", "a", "new", "fence", "."], "concepts": {}, "relations": {}, "covered_token_ids": [], "_concept_id": 0, "_relation_id": 0},
  {"tid": "training-examples.109", "last_saved": "", "annotator": "jdchoi", "tokens": ["The", "boy", "murmured", "softly", "to", "soothe", "the", "girl", ",", "because", "he", "worried", "about", "her", "."], "concepts": {}, "relations": {}, "covered_token_ids": [], "_concept_id": 0, "_relation_id": 0},
  {"tid": "training-examples.110", "last_saved": "", "annotator": "jdchoi", "tokens": ["The", "game", "continued", "despite", "the", "rain", "."], "concepts": {}, "relations": {}, "covered_token_ids": [], "_concept_id": 0, "_relation_id": 0},
  {"tid": "training-examples.111", "last_saved": "", "annotator": "jdchoi", "tokens": ["The", "game", "will", "continue", "even", "if", "it", "rains", "."], "concepts": {}, "relations": {}, "covered_token_ids": [], "_concept_id": 0, "_relation_id": 0},
  {"tid": "training-examples.112", "last_saved": "", "annotator": "jdchoi", "tokens": ["They", "feared", "him", "even", "when", "he", "was", "behind", "bars."], "concepts": {}, "relations": {}, "covered_token_ids": [], "_concept_id": 0, "_relation_id": 0},
  {"tid": "training-examples.113", "last_saved": "", "annotator": "jdchoi", "tokens": ["If", "the", "boy", "is", "given", "money", ",", "he", "will", "sing", "."], "concepts": {}, "relations": {}, "covered_token_ids": [], "_concept_id": 0, "_relation_id": 0},
  {"tid": "training-examples.114", "last_saved": "", "annotator": "jdchoi", "tokens": ["Unless", "the", "boy", "is", "given", "money", ",", "he", "will", "sing", "."], "concepts": {}, "relations": {}, "covered_token_ids": [], "_concept_id": 0, "_relation_id": 0},
  {"tid": "training-examples.115", "last_saved": "", "annotator": "jdchoi", "tokens": ["The", "torpedo", "struck", ",", "damaging", "the", "ship", "."], "concepts": {}, "relations": {}, "covered_token_ids": [], "_concept_id": 0, "_relation_id": 0},
  {"tid": "training-examples.116", "last_saved": "", "annotator": "jdchoi", "tokens": ["The", "boy", "provided", "the", "girl", "with", "chocolate", "."], "concepts": {}, "relations": {}, "covered_token_ids": [], "_concept_id": 0, "_relation_id": 0},
  {"tid": "training-examples.117", "last_saved": "", "annotator": "jdchoi", "tokens": ["They", "built", "the", "bridge", "in", "Maryland", "in", "December", "."], "concepts": {}, "relations": {}, "covered_token_ids": [], "_concept_id": 0, "_relation_id": 0},
  {"tid": "training-examples.118", "last_saved": "", "annotator": "jdchoi", "tokens": ["the", "engine", "of", "the", "car"], "concepts": {}, "relations": {}, "covered_token_ids": [], "_concept_id": 0, "_relation_id": 0},
  {"tid": "training-examples.119", "last_saved": "", "annotator": "jdchoi", "tokens": ["the", "company's", "unit"], "concepts": {}, "relations": {}, "covered_token_ids": [], "_concept_id": 0, "_relation_id": 0},
  {"tid": "training-examples.120", "last_saved": "", "annotator": "jdchoi", "tokens": ["southern", "France"], "concepts": {}, "relations": {}, "covered_token_ids": [], "_concept_id": 0, "_relation_id": 0},
  {"tid": "training-examples.121", "last_saved": "", "annotator": "jdchoi", "tokens": ["The", "boy", "won", "the", "race", "in", "the", "Olympics", "."], "concepts": {}, "relations": {}, "covered_token_ids": [], "_concept_id": 0, "_relation_id": 0},
  {"tid": "training-examples.122", "last_saved": "", "annotator": "jdchoi", "tokens": ["a", "ring", "of", "gold"], "concepts": {}, "relations": {}, "covered_token_ids": [], "_concept_id": 0, "_relation_id": 0},
  {"tid": "training-examples.123", "last_saved": "", "annotator": "jdchoi", "tokens": ["a", "team", "of", "monkeys"], "concepts": {}, "relations": {}, "covered_token_ids": [], "_concept_id": 0, "_relation_id": 0},
  {"tid": "training-examples.124", "last_saved": "", "annotator": "jdchoi", "tokens": ["companies", "like", "IBM", "and", "Google"], "concepts": {}, "relations": {}, "covered_token_ids": [], "_concept_id": 0, "_relation_id": 0},
  {"tid": "training-examples.125", "last_saved": "", "annotator": "jdchoi", "tokens": ["He", "drove", "west", "."], "concepts": {}, "relations": {}, "covered_token_ids": [], "_concept_id": 0, "_relation_id": 0},
  {"tid": "training-examples.126", "last_saved": "", "annotator": "jdchoi", "tokens": ["We", "met", "three", "times", "."], "concepts": {}, "relations": {}, "covered_token_ids": [], "_concept_id": 0, "_relation_id": 0},
  {"tid": "training-examples.127", "last_saved": "", "annotator": "jdchoi", "tokens": ["twice", "a", "year"], "concepts": {}, "relations": {}, "covered_token_ids": [], "_concept_id": 0, "_relation_id": 0},
  {"tid": "training-examples.128", "last_saved": "", "annotator": "jdchoi", "tokens": ["We", "play", "bridge", "every", "Wednesday", "afternoon", "."], "concepts": {}, "relations": {}, "covered_token_ids": [], "_concept_id": 0, "_relation_id": 0},
  {"tid": "training-examples.129", "last_saved": "", "annotator": "jdchoi", "tokens": ["The", "goad", "goes", "on", "forever", "."], "concepts": {}, "relations": {}, "covered_token_ids": [], "_concept_id": 0, "_relation_id": 0},
  {"tid": "training-examples.130", "last_saved": "", "annotator": "jdchoi", "tokens": ["The", "boy", "from", "the", "college", "sang", "."], "concepts": {}, "relations": {}, "covered_token_ids": [], "_concept_id": 0, "_relation_id": 0},
  {"tid": "training-examples.131", "last_saved": "", "annotator": "jdchoi", "tokens": ["the", "singing", "boy", "from", "the", "college"], "concepts": {}, "relations": {}, "covered_token_ids": [], "_concept_id": 0, "_relation_id": 0},
  {"tid": "training-examples.132", "last_saved": "", "annotator": "jdchoi", "tokens": ["the", "college", "that", "the", "singing", "boy", "came", "from"], "concepts": {}, "relations": {}, "covered_token_ids": [], "_concept_id": 0, "_relation_id": 0},
  {"tid": "training-examples.133", "last_saved": "", "annotator": "jdchoi", "tokens": ["The", "girl", "left", "because", "the", "boy", "arrived", "."], "concepts": {}, "relations": {}, "covered_token_ids": [], "_concept_id": 0, "_relation_id": 0},
  {"tid": "training-examples.134", "last_saved": "", "annotator": "jdchoi", "tokens": ["We", "know", "the", "knife", "that", "is", "in", "the", "drawer", "."], "concepts": {}, "relations": {}, "covered_token_ids": [], "_concept_id": 0, "_relation_id": 0},
  {"tid": "training-examples.135", "last_saved": "", "annotator": "jdchoi", "tokens": ["We", "know", "the", "drawer", "where", "the", "knife", "is", "."], "concepts": {}, "relations": {}, "covered_token_ids": [], "_concept_id": 0, "_relation_id": 0},
  {"tid": "training-examples.136", "last_saved": "", "annotator": "jdchoi", "tokens": ["We", "know", "the", "knife", "is", "in", "the", "drawer", "."], "concepts": {}, "relations": {}, "covered_token_ids": [], "_concept_id": 0, "_relation_id": 0},
  {"tid": "training-examples.137", "last_saved": "", "annotator": "jdchoi", "tokens": ["We", "know", "the", "knife", "was", "not", "in", "the", "drawer", "yesterday", "."], "concepts": {}, "relations": {}, "covered_token_ids": [], "_concept_id": 0, "_relation_id": 0},
  {"tid": "training-examples.138", "last_saved": "", "annotator": "jdchoi", "tokens": ["The", "girl", "adjusted", "the", "machine", "."], "concepts": {}, "relations": {}, "covered_token_ids": [], "_concept_id": 0, "_relation_id": 0},
  {"tid": "training-examples.139", "last_saved": "", "annotator": "jdchoi", "tokens": ["The", "boy", "bathed", "."], "concepts": {}, "relations": {}, "covered_token_ids": [], "_concept_id": 0, "_relation_id": 0},
  {"tid": "training-examples.140", "last_saved": "", "annotator": "jdchoi", "tokens": ["The", "boy", "looked", "the", "answer", "up", "."], "concepts": {}, "relations": {}, "covered_token_ids": [], "_concept_id": 0, "_relation_id": 0},
  {"tid": "training-examples.141", "last_saved": "", "annotator": "jdchoi", "tokens": ["The", "nation", "defaulted", "in", "June", "."], "concepts": {}, "relations": {}, "covered_token_ids": [], "_concept_id": 0, "_relation_id": 0},
  {"tid": "training-examples.142", "last_saved": "", "annotator": "jdchoi", "tokens": ["The", "man", "died", "in", "his", "house", "."], "concepts": {}, "relations": {}, "covered_token_ids": [], "_concept_id": 0, "_relation_id": 0},
  {"tid": "training-examples.143", "last_saved": "", "annotator": "jdchoi", "tokens": ["The", "nation", "defaulted", "after", "the", "war", "."], "concepts": {}, "relations": {}, "covered_token_ids": [], "_concept_id": 0, "_relation_id": 0},
  {"tid": "training-examples.144", "last_saved": "", "annotator": "jdchoi", "tokens": ["The", "man", "died", "near", "his", "house", "."], "concepts": {}, "relations": {}, "covered_token_ids": [], "_concept_id": 0, "_relation_id": 0},
  {"tid": "training-examples.145", "last_saved": "", "annotator": "jdchoi", "tokens": ["The", "man", "died", "between", "the", "house", "and", "the", "river", "."], "concepts": {}, "relations": {}, "covered_token_ids": [], "_concept_id": 0, "_relation_id": 0},
  {"tid": "training-examples.146", "last_saved": "", "annotator": "jdchoi", "tokens": ["He", "was", "sued", "in", "the", "case", "."], "concepts": {}, "relations": {}, "covered_token_ids": [], "_concept_id": 0, "_relation_id": 0},
  {"tid": "training-examples.147", "last_saved": "", "annotator": "jdchoi", "tokens": ["The", "brief", "was", "filed", "on", "behalf", "of", "the", "government", "."], "concepts": {}, "relations": {}, "covered_token_ids": [], "_concept_id": 0, "_relation_id": 0},
  {"tid": "training-examples.148", "last_saved": "", "annotator": "jdchoi", "tokens": ["Government", "sources", "said", "that", "the", "killing", "happened", "yesterday", "."], "concepts": {}, "relations": {}, "covered_token_ids": [], "_concept_id": 0, "_relation_id": 0},
  {"tid": "training-examples.149", "last_saved": "", "annotator": "jdchoi", "tokens": ["The", "boy", "believes", "."], "concepts": {}, "relations": {}, "covered_token_ids": [], "_concept_id": 0, "_relation_id": 0},
  {"tid": "training-examples.150", "last_saved": "", "annotator": "jdchoi", "tokens": ["The", "boy", "who", "believes", "."], "concepts": {}, "relations": {}, "covered_token_ids": [], "_concept_id": 0, "_relation_id": 0},
  {"tid": "training-examples.151", "last_saved": "", "annotator": "jdchoi", "tokens": ["the", "black", "car"], "concepts": {}, "relations": {}, "covered_token_ids": [], "_concept_id": 0, "_relation_id": 0},
  {"tid": "training-examples.152", "last_saved": "", "annotator": "jdchoi", "tokens": ["the", "car", "that", "is", "not", "black"], "concepts": {}, "relations": {}, "covered_token_ids": [], "_concept_id": 0, "_relation_id": 0},
  {"tid": "training-examples.153", "last_saved": "", "annotator": "jdchoi", "tokens": ["the", "Shanghai", "legal", "system"], "concepts": {}, "relations": {}, "covered_token_ids": [], "_concept_id": 0, "_relation_id": 0},
  {"tid": "training-examples.154", "last_saved": "", "annotator": "jdchoi", "tokens": ["She", "arrived", "earlier", "today", "."], "concepts": {}, "relations": {}, "covered_token_ids": [], "_concept_id": 0, "_relation_id": 0},
  {"tid": "training-examples.155", "last_saved": "", "annotator": "jdchoi", "tokens": ["the", "boy", "who", "wants", "to", "believe", "the", "girl"], "concepts": {}, "relations": {}, "covered_token_ids": [], "_concept_id": 0, "_relation_id": 0},
  {"tid": "training-examples.156", "last_saved": "", "annotator": "jdchoi", "tokens": ["the", "boy", "and", "the", "girl"], "concepts": {}, "relations": {}, "covered_token_ids": [], "_concept_id": 0, "_relation_id": 0},
  {"tid": "training-examples.157", "last_saved": "", "annotator": "jdchoi", "tokens": ["either", "the", "boy", ",", "the", "girl", ",", "or", "the", "dog"], "concepts": {}, "relations": {}, "covered_token_ids": [], "_concept_id": 0, "_relation_id": 0},
  {"tid": "training-examples.158", "last_saved": "", "annotator": "jdchoi", "tokens": ["the", "big", ",", "heavy", "ball"], "concepts": {}, "relations": {}, "covered_token_ids": [], "_concept_id": 0, "_relation_id": 0},
  {"tid": "training-examples.159", "last_saved": "", "annotator": "jdchoi", "tokens": ["There", "was", "shouting", ",", "and", "the", "boy", "left", "."], "concepts": {}, "relations": {}, "covered_token_ids": [], "_concept_id": 0, "_relation_id": 0},
  {"tid": "training-examples.160", "last_saved": "", "annotator": "jdchoi", "tokens": ["There", "was", "shouting", ",", "but", "the", "boy", "stayed", "."], "concepts": {}, "relations": {}, "covered_token_ids": [], "_concept_id": 0, "_relation_id": 0},
  {"tid": "training-examples.161", "last_saved": "", "annotator": "jdchoi", "tokens": ["But", "the", "boy", "stayed", "."], "concepts": {}, "relations": {}, "covered_token_ids": [], "_concept_id": 0, "_relation_id": 0},
  {"tid": "training-examples.162", "last_saved": "", "annotator": "jdchoi", "tokens": ["The", "boy", "shouted", "and", "left", "."], "concepts": {}, "relations": {}, "covered_token_ids": [], "_concept_id": 0, "_relation_id": 0},
  {"tid": "training-examples.163", "last_saved": "", "annotator": "jdchoi", "tokens": ["The", "boy", "arrived", "and", "was", "promptly", "killed", "."], "concepts": {}, "relations": {}, "covered_token_ids": [], "_concept_id": 0, "_relation_id": 0},
  {"tid": "training-examples.164", "last_saved": "", "annotator": "jdchoi", "tokens": ["The", "boy", "arrived", "and", "left", "on", "Tuesday", "."], "concepts": {}, "relations": {}, "covered_token_ids": [], "_concept_id": 0, "_relation_id": 0},
  {"tid": "training-examples.165", "last_saved": "", "annotator": "jdchoi", "tokens": ["All", "the", "boys", "left", "."], "concepts": {}, "relations": {}, "covered_token_ids": [], "_concept_id": 0, "_relation_id": 0},
  {"tid": "training-examples.166", "last_saved": "", "annotator": "jdchoi", "tokens": ["None", "of", "the", "boys", "left", "."], "concepts": {}, "relations": {}, "covered_token_ids": [], "_concept_id": 0, "_relation_id": 0},
  {"tid": "training-examples.167", "last_saved": "", "annotator": "jdchoi", "tokens": ["Not", "all", "of", "the", "boys", "left", "."], "concepts": {}, "relations": {}, "covered_token_ids": [], "_concept_id": 0, "_relation_id": 0},
  {"tid": "training-examples.168", "last_saved": "", "annotator": "jdchoi", "tokens": ["Not", "everyone", "left", "."], "concepts": {}, "relations": {}, "covered_token_ids": [], "_concept_id": 0, "_relation_id": 0},
  {"tid": "training-examples.169", "last_saved": "", "annotator": "jdchoi", "tokens": ["The", "girl", "believes", "that", "the", "boy", "works", "hard", "."], "concepts": {}, "relations": {}, "covered_token_ids": [], "_concept_id": 0, "_relation_id": 0},
  {"tid": "training-examples.170", "last_saved": "", "annotator": "jdchoi", "tokens": ["The", "girl", "believes", "that", "the", "boy", "does", "n't", "work", "hard", "."], "concepts": {}, "relations": {}, "covered_token_ids": [], "_concept_id": 0, "_relation_id": 0},
  {"tid": "training-examples.171", "last_saved": "", "annotator": "jdchoi", "tokens": ["It", "'s", "not", "true", "that", "the", "girl", "believes", "the", "boy", "works", "hard", "."], "concepts": {}, "relations": {}, "covered_token_ids": [], "_concept_id": 0, "_relation_id": 0},
  {"tid": "training-examples.172", "last_saved": "", "annotator": "jdchoi", "tokens": ["You", "are", "very", "beautiful", "."], "concepts": {}, "relations": {}, "covered_token_ids": [], "_concept_id": 0, "_relation_id": 0},
  {"tid": "training-examples.173", "last_saved": "", "annotator": "jdchoi", "tokens": ["The", "brighter", "boy", "."], "concepts": {}, "relations": {}, "covered_token_ids": [], "_concept_id": 0, "_relation_id": 0},
  {"tid": "training-examples.174", "last_saved": "", "annotator": "jdchoi", "tokens": ["The", "brightest", "boy", "."], "concepts": {}, "relations": {}, "covered_token_ids": [], "_concept_id": 0, "_relation_id": 0},
  {"tid": "training-examples.175", "last_saved": "", "annotator": "jdchoi", "tokens": ["The", "better", "plan", "."], "concepts": {}, "relations": {}, "covered_token_ids": [], "_concept_id": 0, "_relation_id": 0},
  {"tid": "training-examples.176", "last_saved": "", "annotator": "jdchoi", "tokens": ["a", "worse", "plan"], "concepts": {}, "relations": {}, "covered_token_ids": [], "_concept_id": 0, "_relation_id": 0},
  {"tid": "training-examples.177", "last_saved": "", "annotator": "jdchoi", "tokens": ["a", "plan", "that", "is", "too", "extreme"], "concepts": {}, "relations": {}, "covered_token_ids": [], "_concept_id": 0, "_relation_id": 0},
  {"tid": "training-examples.178", "last_saved": "", "annotator": "jdchoi", "tokens": ["The", "girl", "is", "taller", "than", "the", "boy", "."], "concepts": {}, "relations": {}, "covered_token_ids": [], "_concept_id": 0, "_relation_id": 0},
  {"tid": "training-examples.179", "last_saved": "", "annotator": "jdchoi", "tokens": ["She", "is", "the", "tallest", "girl", "on", "the", "team", "."], "concepts": {}, "relations": {}, "covered_token_ids": [], "_concept_id": 0, "_relation_id": 0},
  {"tid": "training-examples.180", "last_saved": "", "annotator": "jdchoi", "tokens": ["It", "is", "too", "early", "to", "reach", "any", "conclusion", "."], "concepts": {}, "relations": {}, "covered_token_ids": [], "_concept_id": 0, "_relation_id": 0},
  {"tid": "training-examples.181", "last_saved": "", "annotator": "jdchoi", "tokens": ["He", "is", "not", "tall", "enough", "to", "ride", "the", "rollercoaster", "."], "concepts": {}, "relations": {}, "covered_token_ids": [], "_concept_id": 0, "_relation_id": 0},
  {"tid": "training-examples.182", "last_saved": "", "annotator": "jdchoi", "tokens": ["The", "boy", "wants", "to", "go", "."], "concepts": {}, "relations": {}, "covered_token_ids": [], "_concept_id": 0, "_relation_id": 0},
  {"tid": "training-examples.183", "last_saved": "", "annotator": "jdchoi", "tokens": ["The", "boy", "wants", "to", "believe", "himself", "."], "concepts": {}, "relations": {}, "covered_token_ids": [], "_concept_id": 0, "_relation_id": 0},
  {"tid": "training-examples.184", "last_saved": "", "annotator": "jdchoi", "tokens": ["He", "saw", "them", "."], "concepts": {}, "relations": {}, "covered_token_ids": [], "_concept_id": 0, "_relation_id": 0},
  {"tid": "training-examples.185", "last_saved": "", "annotator": "jdchoi", "tokens": ["his", "car"], "concepts": {}, "relations": {}, "covered_token_ids": [], "_concept_id": 0, "_relation_id": 0},
  {"tid": "training-examples.186", "last_saved": "", "annotator": "jdchoi", "tokens": ["the", "nation", "'s", "titans"], "concepts": {}, "relations": {}, "covered_token_ids": [], "_concept_id": 0, "_relation_id": 0},
  {"tid": "training-examples.187", "last_saved": "", "annotator": "jdchoi", "tokens": ["atomic", "war"], "concepts": {}, "relations": {}, "covered_token_ids": [], "_concept_id": 0, "_relation_id": 0},
  {"tid": "training-examples.188", "last_saved": "", "annotator": "jdchoi", "tokens": ["behavioral", "problems"], "concepts": {}, "relations": {}, "covered_token_ids": [], "_concept_id": 0, "_relation_id": 0},
  {"tid": "training-examples.189", "last_saved": "", "annotator": "jdchoi", "tokens": ["the", "second", "planet"], "concepts": {}, "relations": {}, "covered_token_ids": [], "_concept_id": 0, "_relation_id": 0},
  {"tid": "training-examples.190", "last_saved": "", "annotator": "jdchoi", "tokens": ["our", "first", "visit", "in", "10", "years"], "concepts": {}, "relations": {}, "covered_token_ids": [], "_concept_id": 0, "_relation_id": 0},
  {"tid": "training-examples.191", "last_saved": "", "annotator": "jdchoi", "tokens": ["Nine", "of", "the", "twenty", "soldiers", "died", "."], "concepts": {}, "relations": {}, "covered_token_ids": [], "_concept_id": 0, "_relation_id": 0},
  {"tid": "training-examples.192", "last_saved": "", "annotator": "jdchoi", "tokens": ["Four", "of", "the", "five", "survivors", "had", "the", "disease", ",", "including", "three", "who", "were", "diagnosed", "."], "concepts": {}, "relations": {}, "covered_token_ids": [], "_concept_id": 0, "_relation_id": 0},
  {"tid": "training-examples.193", "last_saved": "", "annotator": "jdchoi", "tokens": ["The", "Titanic"], "concepts": {}, "relations": {}, "covered_token_ids": [], "_concept_id": 0, "_relation_id": 0},
  {"tid": "training-examples.194", "last_saved": "", "annotator": "jdchoi", "tokens": ["the", "city", "of", "Marina", "del", "Rey"], "concepts": {}, "relations": {}, "covered_token_ids": [], "_concept_id": 0, "_relation_id": 0},
  {"tid": "training-examples.195", "last_saved": "", "annotator": "jdchoi", "tokens": ["Cali"], "concepts": {}, "relations": {}, "covered_token_ids": [], "_concept_id": 0, "_relation_id": 0},
  {"tid": "training-examples.196", "last_saved": "", "annotator": "jdchoi", "tokens": ["advertising", "rates"], "concepts": {}, "relations": {}, "covered_token_ids": [], "_concept_id": 0, "_relation_id": 0},
  {"tid": "training-examples.197", "last_saved": "", "annotator": "jdchoi", "tokens": ["Pascal"], "concepts": {}, "relations": {}, "covered_token_ids": [], "_concept_id": 0, "_relation_id": 0},
  {"tid": "training-examples.198", "last_saved": "", "annotator": "jdchoi", "tokens": ["the", "chip", "maker"], "concepts": {}, "relations": {}, "covered_token_ids": [], "_concept_id": 0, "_relation_id": 0},
  {"tid": "training-examples.199", "last_saved": "", "annotator": "jdchoi", "tokens": ["the", "Nobel", "Prize"], "concepts": {}, "relations": {}, "covered_token_ids": [], "_concept_id": 0, "_relation_id": 0},
  {"tid": "training-examples.200", "last_saved": "", "annotator": "jdchoi", "tokens": ["the", "American", "NSA"], "concepts": {}, "relations": {}, "covered_token_ids": [], "_concept_id": 0, "_relation_id": 0},
  {"tid": "training-examples.201", "last_saved": "", "annotator": "jdchoi", "tokens": ["William", "Shakespeare", ",", "the", "poet"], "concepts": {}, "relations": {}, "covered_token_ids": [], "_concept_id": 0, "_relation_id": 0},
  {"tid": "training-examples.202", "last_saved": "", "annotator": "jdchoi", "tokens": ["the", "village", "of", "Odinaboi"], "concepts": {}, "relations": {}, "covered_token_ids": [], "_concept_id": 0, "_relation_id": 0},
  {"tid": "training-examples.203", "last_saved": "", "annotator": "jdchoi", "tokens": ["Sudan", "'s", "Darfur", "region"], "concepts": {}, "relations": {}, "covered_token_ids": [], "_concept_id": 0, "_relation_id": 0},
  {"tid": "training-examples.204", "last_saved": "", "annotator": "jdchoi", "tokens": ["Germany", "'s", "conservative", "CDU", "party"], "concepts": {}, "relations": {}, "covered_token_ids": [], "_concept_id": 0, "_relation_id": 0},
  {"tid": "training-examples.205", "last_saved": "", "annotator": "jdchoi", "tokens": ["the", "spaceship", "Shenzhou"], "concepts": {}, "relations": {}, "covered_token_ids": [], "_concept_id": 0, "_relation_id": 0},
  {"tid": "training-examples.206", "last_saved": "", "annotator": "jdchoi", "tokens": ["Mr", ".", "Wu"], "concepts": {}, "relations": {}, "covered_token_ids": [], "_concept_id": 0, "_relation_id": 0},
  {"tid": "training-examples.207", "last_saved": "", "annotator": "jdchoi", "tokens": ["the", "poet", "Dr", ".", "Seuss"], "concepts": {}, "relations": {}, "covered_token_ids": [], "_concept_id": 0, "_relation_id": 0},
  {"tid": "training-examples.208", "last_saved": "", "annotator": "jdchoi", "tokens": ["US", "President", "Obama"], "concepts": {}, "relations": {}, "covered_token_ids": [], "_concept_id": 0, "_relation_id": 0},
  {"tid": "training-examples.209", "last_saved": "", "annotator": "jdchoi", "tokens": ["He", "is", "my", "brother", "-", "in", "-", "law", "."], "concepts": {}, "relations": {}, "covered_token_ids": [], "_concept_id": 0, "_relation_id": 0},
  {"tid": "training-examples.210", "last_saved": "", "annotator": "jdchoi", "tokens": ["forty", "thousand", "boys"], "concepts": {}, "relations": {}, "covered_token_ids": [], "_concept_id": 0, "_relation_id": 0},
  {"tid": "training-examples.211", "last_saved": "", "annotator": "jdchoi", "tokens": ["1", ".", "5", "billion", "atoms"], "concepts": {}, "relations": {}, "covered_token_ids": [], "_concept_id": 0, "_relation_id": 0},
  {"tid": "training-examples.212", "last_saved": "", "annotator": "jdchoi", "tokens": ["several", "hundred", "boys"], "concepts": {}, "relations": {}, "covered_token_ids": [], "_concept_id": 0, "_relation_id": 0},
  {"tid": "training-examples.213", "last_saved": "", "annotator": "jdchoi", "tokens": ["more", "than", "four", "thousand", "boys"], "concepts": {}, "relations": {}, "covered_token_ids": [], "_concept_id": 0, "_relation_id": 0},
  {"tid": "training-examples.214", "last_saved": "", "annotator": "jdchoi", "tokens": ["between", "four", "and", "five", "thousand", "boys"], "concepts": {}, "relations": {}, "covered_token_ids": [], "_concept_id": 0, "_relation_id": 0},
  {"tid": "training-examples.215", "last_saved": "", "annotator": "jdchoi", "tokens": ["ten", "miles"], "concepts": {}, "relations": {}, "covered_token_ids": [], "_concept_id": 0, "_relation_id": 0},
  {"tid": "training-examples.216", "last_saved": "", "annotator": "jdchoi", "tokens": ["about", "ten", "miles"], "concepts": {}, "relations": {}, "covered_token_ids": [], "_concept_id": 0, "_relation_id": 0},
  {"tid": "training-examples.217", "last_saved": "", "annotator": "jdchoi", "tokens": ["The", "woman", "bought", "two", "gallons", "of", "milk", "."], "concepts": {}, "relations": {}, "covered_token_ids": [], "_concept_id": 0, "_relation_id": 0},
  {"tid": "training-examples.218", "last_saved": "", "annotator": "jdchoi", "tokens": ["30", "years"], "concepts": {}, "relations": {}, "covered_token_ids": [], "_concept_id": 0, "_relation_id": 0},
  {"tid": "training-examples.219", "last_saved": "", "annotator": "jdchoi", "tokens": ["during", "the", "past", "30", "years"], "concepts": {}, "relations": {}, "covered_token_ids": [], "_concept_id": 0, "_relation_id": 0},
  {"tid": "training-examples.220", "last_saved": "", "annotator": "jdchoi", "tokens": ["30", "years", "ago"], "concepts": {}, "relations": {}, "covered_token_ids": [], "_concept_id": 0, "_relation_id": 0},
  {"tid": "training-examples.221", "last_saved": "", "annotator": "jdchoi", "tokens": ["more", "than", "30", "years", "ago"], "concepts": {}, "relations": {}, "covered_token_ids": [], "_concept_id": 0, "_relation_id": 0},
  {"tid": "training-examples.222", "last_saved": "", "annotator": "jdchoi", "tokens": ["three", "or", "four", "years"], "concepts": {}, "relations": {}, "covered_token_ids": [], "_concept_id": 0, "_relation_id": 0},
  {"tid": "training-examples.223", "last_saved": "", "annotator": "jdchoi", "tokens": ["six", "months", "or", "a", "year"], "concepts": {}, "relations": {}, "covered_token_ids": [], "_concept_id": 0, "_relation_id": 0},
  {"tid": "training-examples.224", "last_saved": "", "annotator": "jdchoi", "tokens": ["The", "plane", "crashed", "50", "miles", "east", "of", "Moscow", "."], "concepts": {}, "relations": {}, "covered_token_ids": [], "_concept_id": 0, "_relation_id": 0},
  {"tid": "training-examples.225", "last_saved": "", "annotator": "jdchoi", "tokens": ["A", "large", "number", "of", "people", "gathered", "."], "concepts": {}, "relations": {}, "covered_token_ids": [], "_concept_id": 0, "_relation_id": 0},
  {"tid": "training-examples.226", "last_saved": "", "annotator": "jdchoi", "tokens": ["The", "number", "of", "people", "increased", "."], "concepts": {}, "relations": {}, "covered_token_ids": [], "_concept_id": 0, "_relation_id": 0},
  {"tid": "training-examples.227", "last_saved": "", "annotator": "jdchoi", "tokens": ["20", "Canadian", "dollars", "."], "concepts": {}, "relations": {}, "covered_token_ids": [], "_concept_id": 0, "_relation_id": 0},
  {"tid": "training-examples.228", "last_saved": "", "annotator": "jdchoi", "tokens": ["7", ".", "9", "on", "the", "Richter", "scale", "."], "concepts": {}, "relations": {}, "covered_token_ids": [], "_concept_id": 0, "_relation_id": 0},
  {"tid": "training-examples.229", "last_saved": "", "annotator": "jdchoi", "tokens": ["He", "sold", "as", "many", "cars", "as", "his", "competitor", "."], "concepts": {}, "relations": {}, "covered_token_ids": [], "_concept_id": 0, "_relation_id": 0},
  {"tid": "training-examples.230", "last_saved": "", "annotator": "jdchoi", "tokens": ["He", "sold", "the", "most", "cars", "of", "his", "competitors", "."], "concepts": {}, "relations": {}, "covered_token_ids": [], "_concept_id": 0, "_relation_id": 0},
  {"tid": "training-examples.231", "last_saved": "", "annotator": "jdchoi", "tokens": ["I", "had", "scarcely", "enough", "drinking", "water", "to", "last", "a", "week", "."], "concepts": {}, "relations": {}, "covered_token_ids": [], "_concept_id": 0, "_relation_id": 0},
  {"tid": "training-examples.232", "last_saved": "", "annotator": "jdchoi", "tokens": ["The", "aircraft", "'s", "velocity", "reached", "three", "times", "the", "speed", "of", "sound", "."], "concepts": {}, "relations": {}, "covered_token_ids": [], "_concept_id": 0, "_relation_id": 0},
  {"tid": "training-examples.233", "last_saved": "", "annotator": "jdchoi", "tokens": ["Patrick", "Makau", "finished", "the", "marathon", "in", "2", "hours", ",", "3", "minutes", ",", "and", "38", "seconds", "."], "concepts": {}, "relations": {}, "covered_token_ids": [], "_concept_id": 0, "_relation_id": 0},
  {"tid": "training-examples.234", "last_saved": "", "annotator": "jdchoi", "tokens": ["February", "29", ",", "2012"], "concepts": {}, "relations": {}, "covered_token_ids": [], "_concept_id": 0, "_relation_id": 0},
  {"tid": "training-examples.235", "last_saved": "", "annotator": "jdchoi", "tokens": ["the", "year", "2012"], "concepts": {}, "relations": {}, "covered_token_ids": [], "_concept_id": 0, "_relation_id": 0},
  {"tid": "training-examples.236", "last_saved": "", "annotator": "jdchoi", "tokens": ["April"], "concepts": {}, "relations": {}, "covered_token_ids": [], "_concept_id": 0, "_relation_id": 0},
  {"tid": "training-examples.237", "last_saved": "", "annotator": "jdchoi", "tokens": ["Friday"], "concepts": {}, "relations": {}, "covered_token_ids": [], "_concept_id": 0, "_relation_id": 0},
  {"tid": "training-examples.238", "last_saved": "", "annotator": "jdchoi", "tokens": ["Wednesday", ",", "February", "29"], "concepts": {}, "relations": {}, "covered_token_ids": [], "_concept_id": 0, "_relation_id": 0},
  {"tid": "training-examples.239", "last_saved": "", "annotator": "jdchoi", "tokens": ["the", "29", "th"], "concepts": {}, "relations": {}, "covered_token_ids": [], "_concept_id": 0, "_relation_id": 0},
  {"tid": "training-examples.240", "last_saved": "", "annotator": "jdchoi", "tokens": ["half", "past", "four"], "concepts": {}, "relations": {}, "covered_token_ids": [], "_concept_id": 0, "_relation_id": 0},
  {"tid": "training-examples.241", "last_saved": "", "annotator": "jdchoi", "tokens": ["4", "th", "quarter", ",", "2011"], "concepts": {}, "relations": {}, "covered_token_ids": [], "_concept_id": 0, "_relation_id": 0},
  {"tid": "training-examples.242", "last_saved": "", "annotator": "jdchoi", "tokens": ["Summer", "2011"], "concepts": {}, "relations": {}, "covered_token_ids": [], "_concept_id": 0, "_relation_id": 0},
  {"tid": "training-examples.243", "last_saved": "", "annotator": "jdchoi", "tokens": ["Winter", "2011", "-", "2012"], "concepts": {}, "relations": {}, "covered_token_ids": [], "_concept_id": 0, "_relation_id": 0},
  {"tid": "training-examples.244", "last_saved": "", "annotator": "jdchoi", "tokens": ["academic", "year", "2011", "-", "2012"], "concepts": {}, "relations": {}, "covered_token_ids": [], "_concept_id": 0, "_relation_id": 0},
  {"tid": "training-examples.245", "last_saved": "", "annotator": "jdchoi", "tokens": ["United", "States", "government", "fiscal", "year", "2012"], "concepts": {}, "relations": {}, "covered_token_ids": [], "_concept_id": 0, "_relation_id": 0},
  {"tid": "training-examples.246", "last_saved": "", "annotator": "jdchoi", "tokens": ["25", "%"], "concepts": {}, "relations": {}, "covered_token_ids": [], "_concept_id": 0, "_relation_id": 0},
  {"tid": "training-examples.247", "last_saved": "", "annotator": "jdchoi", "tokens": ["1", "(800)", "555", "-", "1212"], "concepts": {}, "relations": {}, "covered_token_ids": [], "_concept_id": 0, "_relation_id": 0},
  {"tid": "training-examples.248", "last_saved": "", "annotator": "jdchoi", "tokens": ["president@whitehouse.gov"], "concepts": {}, "relations": {}, "covered_token_ids": [], "_concept_id": 0, "_relation_id": 0},
  {"tid": "training-examples.249", "last_saved": "", "annotator": "jdchoi", "tokens": ["The", "woman", "who", "lost", "her", "scarf", "."], "concepts": {}, "relations": {}, "covered_token_ids": [], "_concept_id": 0, "_relation_id": 0}
]
